<NetConnectResponse xmlns="http://www.experian.com/NetConnectResponse"><CompletionCode>0000</CompletionCode><ReferenceId/><Products><PreciseIDServer><XMLVersion>5.0</XMLVersion><SessionID>C0TARQIPAHRWFA7RMQ0BFIGS.pidd1v-1805111250420210040637154</SessionID><Header><ReportDate>05112018</ReportDate><ReportTime>125042</ReportTime><Preamble>TBD1</Preamble><ReferenceNumber/></Header><Messages><Message><Number>57</Number><Text>0150          </Text><AddrMismatch>N</AddrMismatch></Message></Messages><Summary><ReviewReferenceID>30064763</ReviewReferenceID><PreciseIDType>18</PreciseIDType><InitialResults><FinalDecision>XXX</FinalDecision></InitialResults></Summary><CCNumerics/><CCStrings><CCString5>X;;;</CCString5></CCStrings><KBAScore><General><KBAResultCode>0</KBAResultCode><KBAResultCodeDescription>KBA processing successful questions returned</KBAResultCodeDescription><PriorUsage><ExceededUseLimitCode>N</ExceededUseLimitCode><ConsumerTotal/><ClientUseLimitPeriod>720</ClientUseLimitPeriod><ClientUseLimitCount>0</ClientUseLimitCount><TotalUseLimitPeriod>720</TotalUseLimitPeriod><TotalUseLimitCount>0</TotalUseLimitCount><ConsumerSSNTotal>0</ConsumerSSNTotal><ClientSSNUseLimitPeriod>0</ClientSSNUseLimitPeriod><ClientSSNUseLimitCount>0</ClientSSNUseLimitCount><TotalSSNUseLimitPeriod>0</TotalSSNUseLimitPeriod><TotalSSNUseLimitCount>0</TotalSSNUseLimitCount><ConcurrentPINTotal>0</ConcurrentPINTotal><ClientConcurrentPINLimitCount>0</ClientConcurrentPINLimitCount><CompanyConcurrentPINLimitCount>0</CompanyConcurrentPINLimitCount><GlobalConcurrentPINLimitCount>0</GlobalConcurrentPINLimitCount></PriorUsage></General><ScoreSummary><AcceptReferCode>ACC</AcceptReferCode><DecisionOverrideIndicator>N</DecisionOverrideIndicator><DecisionOverrideReason/><PreciseIDScore>426</PreciseIDScore><OutWalletScore>100</OutWalletScore><OutWalletFormula>(385/385)*100</OutWalletFormula><ProgressiveQuestionAchieved>Y</ProgressiveQuestionAchieved><ChampionChallengerIndicator>N</ChampionChallengerIndicator><RiskStrategyNum>1</RiskStrategyNum><RiskStrategyDescription>Default Risk Strategy</RiskStrategyDescription><QuestionConfigNum>1</QuestionConfigNum><QuestionConfigDescription>Default Question Configuration                                                                      </QuestionConfigDescription><DecisionMatrixNum>1</DecisionMatrixNum><DecisionMatrixDescription>Default Decision Matrix</DecisionMatrixDescription><UserDefinedParameters><UserDefinedTextName1/><UserDefinedTextValue1/><UserDefinedTextName2/><UserDefinedTextValue2/><UserDefinedTextName3/><UserDefinedTextValue3/><UserDefinedTextName4/><UserDefinedTextValue4/><UserDefinedNumName1/><UserDefinedNumValue1/><UserDefinedNumName2/><UserDefinedNumValue2/><UserDefinedNumName3/><UserDefinedNumValue3/><UserDefinedNumName4/><UserDefinedNumValue4/><UserDefinedDateName1/><UserDefinedDateValue1/><UserDefinedDateName2/><UserDefinedDateValue2/></UserDefinedParameters></ScoreSummary><GradedAnswer><AnswerSet><QuestionType>23</QuestionType><QuestionTypeDescription>PREVIOUS CURRENT EMPLOYER</QuestionTypeDescription><CreditType>N</CreditType><AnswerResult>R</AnswerResult><QuestionWeight>151</QuestionWeight></AnswerSet><AnswerSet><QuestionType>28</QuestionType><QuestionTypeDescription>VEHICLE YEAR</QuestionTypeDescription><CreditType>N</CreditType><AnswerResult>R</AnswerResult><QuestionWeight>117</QuestionWeight></AnswerSet><AnswerSet><QuestionType>47</QuestionType><QuestionTypeDescription>HOME EQUITY LINE OF CREDIT - DIV MIRROR</QuestionTypeDescription><CreditType>C</CreditType><AnswerResult>R</AnswerResult><QuestionWeight>117</QuestionWeight></AnswerSet><AnswerSet><QuestionType>38</QuestionType><QuestionTypeDescription>OTHER FINANCIAL INSTITUTIONS WHERE CONSUMER HAS ACCOUNT - DIV</QuestionTypeDescription><CreditType>C</CreditType><AnswerResult/><QuestionWeight>0</QuestionWeight></AnswerSet></GradedAnswer></KBAScore><EmailAddress><ValidationResultCode code="E701">Invalid format</ValidationResultCode></EmailAddress></PreciseIDServer></Products></NetConnectResponse>